niiprep/__init__.py
niiprep/clean_background.py
niiprep/cli.py
niiprep/crop.py
niiprep/denoise_mp2rage.py
niiprep/nii2mp4.py
niiprep/registration.py
niiprep/resample.py
niiprep/round.py
niiprep-0.1.3.dist-info/METADATA
niiprep-0.1.3.dist-info/WHEEL
niiprep-0.1.3.dist-info/entry_points.txt
niiprep-0.1.3.dist-info/top_level.txt
niiprep-0.1.3.dist-info/RECORD
